Metadata-Version: 2.1
Name: Clists
Version: 0.0.9
Summary: A simple package to hyper-optimise list operations by caching.
Home-page: 
Author: Seth Brockman
Author-email: brockman.seth@google.com
License: MIT
Keywords: list caching,caching,list,list optimisation,list operations
Classifier: Development Status :: 5 - Production/Stable
Classifier: Intended Audience :: Developers
Classifier: Operating System :: OS Independent
Classifier: License :: OSI Approved :: MIT License
Classifier: Programming Language :: Python :: 3
License-File: LICENCE.txt
